evakit/__init__.py
evakit/__version__.py
evakit/args_base.py
evakit/cronjob.py
evakit/launcher_base.py
evakit/logging_utils.py
evakit/python_tricks.py
evakit/singleton.py
evakit-0.3.0.dist-info/licenses/LICENSE
evakit-0.3.0.dist-info/METADATA
evakit-0.3.0.dist-info/WHEEL
evakit-0.3.0.dist-info/top_level.txt
evakit-0.3.0.dist-info/RECORD
