Metadata-Version: 2.4
Name: evakit
Version: 0.3.0
Summary: A collection of utilities for the eva project.
Author-email: Gary Wei <garywei944@gmail.com>
License-Expression: MIT
Classifier: Intended Audience :: Developers
Classifier: Natural Language :: English
Classifier: Operating System :: OS Independent
Classifier: Programming Language :: Python :: 3
Classifier: Programming Language :: Python :: 3.11
Classifier: Programming Language :: Python :: 3.12
Classifier: Programming Language :: Python :: 3.13
Classifier: Programming Language :: Python :: 3.14
Requires-Python: >=3.11
License-File: LICENSE
Requires-Dist: typed-argument-parser
Requires-Dist: psutil
Requires-Dist: typing-extensions
Dynamic: license-file
